[
  {
    "uid": 1,
    "position": [
      4249.854,
      5126.213,
      120.0
    ],
    "weapons": {
      "1": 100,
      "2": 100,
      "3": 1000,
      "4": 1000
    },
    "name": "T96A",
    "side": "red"
  },
  {
    "uid": 2,
    "position": [
      4274.237,
      5080.106,
      117.0
    ],
    "weapons": {
      "1": 100,
      "2": 100,
      "3": 1000,
      "4": 1000
    },
    "name": "T96A",
    "side": "red"
  },
  {
    "uid": 3,
    "position": [
      4301.861,
      5037.903,
      115.0
    ],
    "weapons": {
      "1": 100,
      "2": 100,
      "3": 1000,
      "4": 1000
    },
    "name": "T96A",
    "side": "red"
  },
  {
    "uid": 4,
    "position": [
      4327.865,
      5007.022,
      109.0
    ],
    "weapons": {
      "1": 100,
      "2": 100,
      "3": 1000,
      "4": 1000
    },
    "name": "T96A",
    "side": "red"
  },
  {
    "uid": 7,
    "position": [
      4222.117,
      5339.668,
      156.0
    ],
    "weapons": {
      "1": 100,
      "2": 100,
      "3": 1000,
      "4": 1000
    },
    "name": "侦打无人车",
    "side": "red"
  },
  {
    "uid": 8,
    "position": [
      4198.836,
      5325.341,
      144.0
    ],
    "weapons": {
      "1": 100,
      "2": 100,
      "3": 1000,
      "4": 1000
    },
    "name": "侦打无人车",
    "side": "red"
  },
  {
    "uid": 9,
    "position": [
      4169.735,
      5313.253,
      132.0
    ],
    "weapons": {
      "1": 100,
      "2": 100,
      "3": 1000,
      "4": 1000
    },
    "name": "侦打无人车",
    "side": "red"
  },
  {
    "uid": 10,
    "position": [
      4093.06,
      5253.704,
      89.0
    ],
    "weapons": {
      "1": 100,
      "2": 100,
      "3": 1000,
      "4": 1000
    },
    "name": "侦打无人车",
    "side": "red"
  },
  {
    "uid": 97,
    "position": [
      4238.25,
      5231.767,
      140.0
    ],
    "weapons": {
      "1": 100,
      "2": 100,
      "3": 1000,
      "4": 1000
    },
    "name": "红方士兵",
    "side": "red"
  },
  {
    "uid": 65,
    "position": [
      4238.25,
      5231.767,
      140.0
    ],
    "weapons": {
      "1": 100,
      "2": 100,
      "3": 1000,
      "4": 1000
    },
    "name": "红方士兵",
    "side": "red"
  },
  {
    "uid": 67,
    "position": [
      4238.25,
      5231.767,
      140.0
    ],
    "weapons": {
      "1": 100,
      "2": 100,
      "3": 1000,
      "4": 1000
    },
    "name": "红方士兵",
    "side": "red"
  },
  {
    "uid": 63,
    "position": [
      4238.25,
      5231.767,
      140.0
    ],
    "weapons": {
      "1": 100,
      "2": 100,
      "3": 1000,
      "4": 1000
    },
    "name": "红方士兵",
    "side": "red"
  },
  {
    "uid": 64,
    "position": [
      4238.25,
      5231.767,
      140.0
    ],
    "weapons": {
      "1": 100,
      "2": 100,
      "3": 1000,
      "4": 1000
    },
    "name": "红方士兵",
    "side": "red"
  },
  {
    "uid": 66,
    "position": [
      4238.25,
      5231.767,
      140.0
    ],
    "weapons": {
      "1": 100,
      "2": 100,
      "3": 1000,
      "4": 1000
    },
    "name": "红方士兵",
    "side": "red"
  },
  {
    "uid": 5,
    "position": [
      4238.25,
      5231.767,
      140.0
    ],
    "weapons": {
      "1": 100,
      "2": 100,
      "3": 1000,
      "4": 1000
    },
    "name": "04A",
    "side": "red"
  },
  {
    "uid": 70,
    "position": [
      4193.031,
      5203.54,
      121.0
    ],
    "weapons": {
      "1": 100,
      "2": 100,
      "3": 1000,
      "4": 1000
    },
    "name": "红方士兵",
    "side": "red"
  },
  {
    "uid": 72,
    "position": [
      4193.031,
      5203.54,
      121.0
    ],
    "weapons": {
      "1": 100,
      "2": 100,
      "3": 1000,
      "4": 1000
    },
    "name": "红方士兵",
    "side": "red"
  },
  {
    "uid": 68,
    "position": [
      4193.031,
      5203.54,
      121.0
    ],
    "weapons": {
      "1": 100,
      "2": 100,
      "3": 1000,
      "4": 1000
    },
    "name": "红方士兵",
    "side": "red"
  },
  {
    "uid": 69,
    "position": [
      4193.031,
      5203.54,
      121.0
    ],
    "weapons": {
      "1": 100,
      "2": 100,
      "3": 1000,
      "4": 1000
    },
    "name": "红方士兵",
    "side": "red"
  },
  {
    "uid": 71,
    "position": [
      4193.031,
      5203.54,
      121.0
    ],
    "weapons": {
      "1": 100,
      "2": 100,
      "3": 1000,
      "4": 1000
    },
    "name": "红方士兵",
    "side": "red"
  },
  {
    "uid": 6,
    "position": [
      4193.031,
      5203.54,
      121.0
    ],
    "weapons": {
      "1": 100,
      "2": 100,
      "3": 1000,
      "4": 1000
    },
    "name": "04A",
    "side": "red"
  },
  {
    "uid": 25,
    "position": [
      4470.5,
      4321.038,
      31.0
    ],
    "weapons": {
      "1": 100,
      "2": 100,
      "3": 1000,
      "4": 1000
    },
    "name": "运载车",
    "side": "red"
  },
  {
    "uid": 26,
    "position": [
      4452.255,
      4435.253,
      39.0
    ],
    "weapons": {
      "1": 100,
      "2": 100,
      "3": 1000,
      "4": 1000
    },
    "name": "运载车",
    "side": "red"
  },
  {
    "uid": 27,
    "position": [
      4400.703,
      4290.103,
      16.0
    ],
    "weapons": {
      "1": 100,
      "2": 100,
      "3": 1000,
      "4": 1000
    },
    "name": "运载车",
    "side": "red"
  },
  {
    "uid": 28,
    "position": [
      4306.318,
      4325.796,
      6.0
    ],
    "weapons": {
      "1": 100,
      "2": 100,
      "3": 1000,
      "4": 1000
    },
    "name": "运载车",
    "side": "red"
  },
  {
    "uid": 29,
    "position": [
      4302.349,
      4446.355,
      18.0
    ],
    "weapons": {
      "1": 100,
      "2": 100,
      "3": 1000,
      "4": 1000
    },
    "name": "运载车",
    "side": "red"
  },
  {
    "uid": 30,
    "position": [
      4391.182,
      4510.601,
      35.0
    ],
    "weapons": {
      "1": 100,
      "2": 100,
      "3": 1000,
      "4": 1000
    },
    "name": "运载车",
    "side": "red"
  },
  {
    "uid": 11,
    "position": [
      4045.928,
      5238.855,
      60.0
    ],
    "weapons": {
      "1": 100,
      "2": 100,
      "3": 1000,
      "4": 1000
    },
    "name": "侦打无人车",
    "side": "red"
  },
  {
    "uid": 12,
    "position": [
      3996.607,
      5197.491,
      36.0
    ],
    "weapons": {
      "1": 100,
      "2": 100,
      "3": 1000,
      "4": 1000
    },
    "name": "侦打无人车",
    "side": "red"
  },
  {
    "uid": 19,
    "position": [
      4391.919,
      4989.94,
      116.0
    ],
    "weapons": {
      "1": 100,
      "2": 100,
      "3": 1000,
      "4": 1000
    },
    "name": "补给车",
    "side": "red"
  },
  {
    "uid": 20,
    "position": [
      4356.704,
      4951.484,
      95.0
    ],
    "weapons": {
      "1": 100,
      "2": 100,
      "3": 1000,
      "4": 1000
    },
    "name": "补给车",
    "side": "red"
  },
  {
    "uid": 21,
    "position": [
      4321.491,
      4905.441,
      71.0
    ],
    "weapons": {
      "1": 100,
      "2": 100,
      "3": 1000,
      "4": 1000
    },
    "name": "补给车",
    "side": "red"
  },
  {
    "uid": 22,
    "position": [
      4285.195,
      4849.642,
      44.0
    ],
    "weapons": {
      "1": 100,
      "2": 100,
      "3": 1000,
      "4": 1000
    },
    "name": "补给车",
    "side": "red"
  },
  {
    "uid": 23,
    "position": [
      4253.803,
      4811.182,
      34.0
    ],
    "weapons": {
      "1": 100,
      "2": 100,
      "3": 1000,
      "4": 1000
    },
    "name": "补给车",
    "side": "red"
  },
  {
    "uid": 24,
    "position": [
      4201.241,
      4769.468,
      26.0
    ],
    "weapons": {
      "1": 100,
      "2": 100,
      "3": 1000,
      "4": 1000
    },
    "name": "补给车",
    "side": "red"
  },
  {
    "uid": 13,
    "position": [
      4454.943,
      4317.831,
      27.0
    ],
    "weapons": {
      "1": 100,
      "2": 100,
      "3": 1000,
      "4": 1000
    },
    "name": "红方无人机",
    "side": "red"
  },
  {
    "uid": 14,
    "position": [
      4380.084,
      4287.788,
      11.0
    ],
    "weapons": {
      "1": 100,
      "2": 100,
      "3": 1000,
      "4": 1000
    },
    "name": "红方无人机",
    "side": "red"
  },
  {
    "uid": 15,
    "position": [
      4287.99,
      4324.232,
      2.0
    ],
    "weapons": {
      "1": 100,
      "2": 100,
      "3": 1000,
      "4": 1000
    },
    "name": "红方无人机",
    "side": "red"
  },
  {
    "uid": 16,
    "position": [
      4432.78,
      4434.057,
      35.0
    ],
    "weapons": {
      "1": 100,
      "2": 100,
      "3": 1000,
      "4": 1000
    },
    "name": "红方无人机",
    "side": "red"
  },
  {
    "uid": 17,
    "position": [
      4373.191,
      4506.458,
      31.0
    ],
    "weapons": {
      "1": 100,
      "2": 100,
      "3": 1000,
      "4": 1000
    },
    "name": "红方无人机",
    "side": "red"
  },
  {
    "uid": 18,
    "position": [
      4283.558,
      4442.426,
      14.0
    ],
    "weapons": {
      "1": 100,
      "2": 100,
      "3": 1000,
      "4": 1000
    },
    "name": "红方无人机",
    "side": "red"
  },
  {
    "uid": 74,
    "position": [
      1781.812,
      8392.812,
      97.0
    ],
    "weapons": {
      "1": 100,
      "2": 100,
      "3": 1000,
      "4": 1000
    },
    "name": "蓝方士兵",
    "side": "blue"
  },
  {
    "uid": 76,
    "position": [
      1828.312,
      8438.438,
      99.0
    ],
    "weapons": {
      "1": 100,
      "2": 100,
      "3": 1000,
      "4": 1000
    },
    "name": "蓝方士兵",
    "side": "blue"
  },
  {
    "uid": 78,
    "position": [
      1705.75,
      8316.25,
      93.0
    ],
    "weapons": {
      "1": 100,
      "2": 100,
      "3": 1000,
      "4": 1000
    },
    "name": "蓝方士兵",
    "side": "blue"
  },
  {
    "uid": 73,
    "position": [
      1797.812,
      8407.75,
      98.0
    ],
    "weapons": {
      "1": 100,
      "2": 100,
      "3": 1000,
      "4": 1000
    },
    "name": "蓝方士兵",
    "side": "blue"
  },
  {
    "uid": 75,
    "position": [
      1812.375,
      8421.312,
      99.0
    ],
    "weapons": {
      "1": 100,
      "2": 100,
      "3": 1000,
      "4": 1000
    },
    "name": "蓝方士兵",
    "side": "blue"
  },
  {
    "uid": 77,
    "position": [
      1752.0,
      8361.688,
      96.0
    ],
    "weapons": {
      "1": 100,
      "2": 100,
      "3": 1000,
      "4": 1000
    },
    "name": "蓝方士兵",
    "side": "blue"
  },
  {
    "uid": 35,
    "position": [
      1749.207,
      8423.522,
      99.0
    ],
    "weapons": {
      "1": 100,
      "2": 100,
      "3": 1000,
      "4": 1000
    },
    "name": "M2A3",
    "side": "blue"
  },
  {
    "uid": 80,
    "position": [
      2029.938,
      8583.875,
      109.0
    ],
    "weapons": {
      "1": 100,
      "2": 100,
      "3": 1000,
      "4": 1000
    },
    "name": "蓝方士兵",
    "side": "blue"
  },
  {
    "uid": 82,
    "position": [
      2090.0,
      8624.062,
      112.0
    ],
    "weapons": {
      "1": 100,
      "2": 100,
      "3": 1000,
      "4": 1000
    },
    "name": "蓝方士兵",
    "side": "blue"
  },
  {
    "uid": 84,
    "position": [
      1929.438,
      8517.812,
      104.0
    ],
    "weapons": {
      "1": 100,
      "2": 100,
      "3": 1000,
      "4": 1000
    },
    "name": "蓝方士兵",
    "side": "blue"
  },
  {
    "uid": 79,
    "position": [
      2050.188,
      8596.812,
      110.0
    ],
    "weapons": {
      "1": 100,
      "2": 100,
      "3": 1000,
      "4": 1000
    },
    "name": "蓝方士兵",
    "side": "blue"
  },
  {
    "uid": 81,
    "position": [
      2070.062,
      8610.625,
      111.0
    ],
    "weapons": {
      "1": 100,
      "2": 100,
      "3": 1000,
      "4": 1000
    },
    "name": "蓝方士兵",
    "side": "blue"
  },
  {
    "uid": 83,
    "position": [
      1989.875,
      8555.688,
      107.0
    ],
    "weapons": {
      "1": 100,
      "2": 100,
      "3": 1000,
      "4": 1000
    },
    "name": "蓝方士兵",
    "side": "blue"
  },
  {
    "uid": 36,
    "position": [
      2012.598,
      8637.304,
      112.0
    ],
    "weapons": {
      "1": 100,
      "2": 100,
      "3": 1000,
      "4": 1000
    },
    "name": "M2A3",
    "side": "blue"
  },
  {
    "uid": 86,
    "position": [
      1832.562,
      8693.438,
      111.0
    ],
    "weapons": {
      "1": 100,
      "2": 100,
      "3": 1000,
      "4": 1000
    },
    "name": "蓝方士兵",
    "side": "blue"
  },
  {
    "uid": 88,
    "position": [
      1881.25,
      8725.062,
      113.0
    ],
    "weapons": {
      "1": 100,
      "2": 100,
      "3": 1000,
      "4": 1000
    },
    "name": "蓝方士兵",
    "side": "blue"
  },
  {
    "uid": 90,
    "position": [
      1756.625,
      8639.312,
      106.0
    ],
    "weapons": {
      "1": 100,
      "2": 100,
      "3": 1000,
      "4": 1000
    },
    "name": "蓝方士兵",
    "side": "blue"
  },
  {
    "uid": 85,
    "position": [
      1850.25,
      8703.312,
      112.0
    ],
    "weapons": {
      "1": 100,
      "2": 100,
      "3": 1000,
      "4": 1000
    },
    "name": "蓝方士兵",
    "side": "blue"
  },
  {
    "uid": 87,
    "position": [
      1865.375,
      8712.75,
      112.0
    ],
    "weapons": {
      "1": 100,
      "2": 100,
      "3": 1000,
      "4": 1000
    },
    "name": "蓝方士兵",
    "side": "blue"
  },
  {
    "uid": 89,
    "position": [
      1803.188,
      8668.062,
      109.0
    ],
    "weapons": {
      "1": 100,
      "2": 100,
      "3": 1000,
      "4": 1000
    },
    "name": "蓝方士兵",
    "side": "blue"
  },
  {
    "uid": 37,
    "position": [
      1818.035,
      8725.044,
      112.0
    ],
    "weapons": {
      "1": 100,
      "2": 100,
      "3": 1000,
      "4": 1000
    },
    "name": "M2A3",
    "side": "blue"
  },
  {
    "uid": 92,
    "position": [
      1836.201,
      8645.056,
      110.0
    ],
    "weapons": {
      "1": 100,
      "2": 100,
      "3": 1000,
      "4": 1000
    },
    "name": "蓝方士兵",
    "side": "blue"
  },
  {
    "uid": 94,
    "position": [
      1836.201,
      8645.056,
      110.0
    ],
    "weapons": {
      "1": 100,
      "2": 100,
      "3": 1000,
      "4": 1000
    },
    "name": "蓝方士兵",
    "side": "blue"
  },
  {
    "uid": 96,
    "position": [
      1836.201,
      8645.056,
      110.0
    ],
    "weapons": {
      "1": 100,
      "2": 100,
      "3": 1000,
      "4": 1000
    },
    "name": "蓝方士兵",
    "side": "blue"
  },
  {
    "uid": 91,
    "position": [
      1836.201,
      8645.056,
      110.0
    ],
    "weapons": {
      "1": 100,
      "2": 100,
      "3": 1000,
      "4": 1000
    },
    "name": "蓝方士兵",
    "side": "blue"
  },
  {
    "uid": 93,
    "position": [
      1836.201,
      8645.056,
      110.0
    ],
    "weapons": {
      "1": 100,
      "2": 100,
      "3": 1000,
      "4": 1000
    },
    "name": "蓝方士兵",
    "side": "blue"
  },
  {
    "uid": 95,
    "position": [
      1836.201,
      8645.056,
      110.0
    ],
    "weapons": {
      "1": 100,
      "2": 100,
      "3": 1000,
      "4": 1000
    },
    "name": "蓝方士兵",
    "side": "blue"
  },
  {
    "uid": 38,
    "position": [
      1836.201,
      8645.056,
      110.0
    ],
    "weapons": {
      "1": 100,
      "2": 100,
      "3": 1000,
      "4": 1000
    },
    "name": "M2A3",
    "side": "blue"
  },
  {
    "uid": 31,
    "position": [
      3235.576,
      7423.708,
      132.0
    ],
    "weapons": {
      "1": 100,
      "2": 100,
      "3": 1000,
      "4": 1000
    },
    "name": "M1A2",
    "side": "blue"
  },
  {
    "uid": 32,
    "position": [
      2814.968,
      7127.929,
      78.0
    ],
    "weapons": {
      "1": 100,
      "2": 100,
      "3": 1000,
      "4": 1000
    },
    "name": "M1A2",
    "side": "blue"
  },
  {
    "uid": 33,
    "position": [
      3178.947,
      7004.86,
      79.0
    ],
    "weapons": {
      "1": 100,
      "2": 100,
      "3": 1000,
      "4": 1000
    },
    "name": "M1A2",
    "side": "blue"
  },
  {
    "uid": 34,
    "position": [
      3369.017,
      7139.991,
      100.0
    ],
    "weapons": {
      "1": 100,
      "2": 100,
      "3": 1000,
      "4": 1000
    },
    "name": "M1A2",
    "side": "blue"
  },
  {
    "uid": 39,
    "position": [
      1936.201,
      8727.186,
      114.0
    ],
    "weapons": {
      "1": 100,
      "2": 100,
      "3": 1000,
      "4": 1000
    },
    "name": "蓝方无人机",
    "side": "blue"
  },
  {
    "uid": 40,
    "position": [
      1692.474,
      8494.78,
      98.0
    ],
    "weapons": {
      "1": 100,
      "2": 100,
      "3": 1000,
      "4": 1000
    },
    "name": "蓝方无人机",
    "side": "blue"
  },
  {
    "uid": 41,
    "position": [
      1808.675,
      8746.251,
      112.0
    ],
    "weapons": {
      "1": 100,
      "2": 100,
      "3": 1000,
      "4": 1000
    },
    "name": "蓝方无人机",
    "side": "blue"
  }
]